garpixcms/CHANGELOG.md
garpixcms/CONTRIBUTING.md
garpixcms/MANIFEST.in
garpixcms/README.rst
garpixcms/__init__.py
garpixcms/apps.py
garpixcms/settings.py
garpixcms/setup.py
garpixcms/urls.py
garpixcms/__pycache__/__init__.cpython-38.pyc
garpixcms/__pycache__/apps.cpython-38.pyc
garpixcms/__pycache__/settings.cpython-38.pyc
garpixcms/__pycache__/urls.cpython-38.pyc
garpixcms/admin/__init__.py
garpixcms/admin/page.py
garpixcms/admin/__pycache__/__init__.cpython-38.pyc
garpixcms/admin/__pycache__/page.cpython-38.pyc
garpixcms/contexts/__init__.py
garpixcms/contexts/global_context.py
garpixcms/management/__init__.py
garpixcms/management/__pycache__/__init__.cpython-38.pyc
garpixcms/management/commands/__init__.py
garpixcms/management/commands/update_user_module.py
garpixcms/middleware/__init__.py
garpixcms/middleware/locale.py
garpixcms/middleware/__pycache__/__init__.cpython-38.pyc
garpixcms/middleware/__pycache__/locale.cpython-38.pyc
garpixcms/models/__init__.py
garpixcms/models/page.py
garpixcms/models/__pycache__/__init__.cpython-38.pyc
garpixcms/models/__pycache__/page.cpython-38.pyc
garpixcms/static/admin/css/autocomplete.css
garpixcms/static/admin/css/base.css
garpixcms/static/admin/css/changelists.css
garpixcms/static/admin/css/dashboard.css
garpixcms/static/admin/css/fonts.css
garpixcms/static/admin/css/forms.css
garpixcms/static/admin/css/login.css
garpixcms/static/admin/css/nav_sidebar.css
garpixcms/static/admin/css/responsive.css
garpixcms/static/admin/css/responsive_rtl.css
garpixcms/static/admin/css/rtl.css
garpixcms/static/admin/css/tabbed_translation_fields.css
garpixcms/static/admin/css/widgets.css
garpixcms/static/admin/img/icon-addlink.svg
garpixcms/static/admin/img/icon-changelink.svg
garpixcms/static/admin/img/icon-custom-checked.svg
garpixcms/static/admin/img/icon-deletelink.svg
garpixcms/static/admin/img/search.svg
garpixcms/static/admin/js/admin.js
garpixcms/templates/admin/app_list.html
garpixcms/templates/admin/base.html
garpixcms-4.5.2.dist-info/METADATA
garpixcms-4.5.2.dist-info/WHEEL
garpixcms-4.5.2.dist-info/top_level.txt
garpixcms-4.5.2.dist-info/RECORD
