Metadata-Version: 2.1
Name: garpixcms
Version: 4.5.2
Home-page: https://github.com/garpixcms/garpixcms
Author: Garpix LTD
Author-email: info@garpix.com
License: MIT
Classifier: Development Status :: 4 - Beta
Classifier: Environment :: Web Environment
Classifier: Intended Audience :: Developers
Classifier: License :: OSI Approved :: MIT License
Classifier: Operating System :: OS Independent
Classifier: Programming Language :: Python
Classifier: Framework :: Django
Classifier: Programming Language :: Python :: 3.8
Requires-Dist: Django (<4,>=3.1)
Requires-Dist: garpix-utils (==1.9.0)
Requires-Dist: garpix-page (==2.48.2)
Requires-Dist: garpix-menu (==1.16.0)
Requires-Dist: eqator (==2.7.0)
Requires-Dist: garpix-auth (==2.3.0)
Requires-Dist: garpix-notify (==5.16.2)
Requires-Dist: garpix-user (==3.9.1)
Requires-Dist: garpix-package (==2.0.1)
Requires-Dist: psycopg2-binary (>=2.8.6)
Requires-Dist: uwsgi (>=2.0.19.1)
Requires-Dist: environs (>=9.3.2)
Requires-Dist: django-ckeditor (==6.3.0)
Requires-Dist: djangorestframework (>=3.12.4)
Requires-Dist: django-cors-headers (<=3.13.0,>=3.7.0)
Requires-Dist: drf-spectacular (>=0.18.2)
Requires-Dist: sentry-sdk (>=1.5.2)
Requires-Dist: pre-commit (>=2.17.0)
Requires-Dist: django-tabbed-admin (>=1.0.4)
